rhpaste/__init__.py
rhpaste/__version__.py
rhpaste/core.py
rhpaste-0.1.6.dist-info/METADATA
rhpaste-0.1.6.dist-info/WHEEL
rhpaste-0.1.6.dist-info/entry_points.txt
rhpaste-0.1.6.dist-info/top_level.txt
rhpaste-0.1.6.dist-info/RECORD
