Metadata-Version: 2.1
Name: rhpaste
Version: 0.1.6
Summary: Red Hat Pastebin CLI tool
Home-page: https://sr.ht/~joshmulliken/redhat-pastebin-cli/
Author: Joshua Mulliken
Author-email: joshua@mulliken.net
License: MIT
Platform: UNKNOWN
Classifier: License :: OSI Approved :: GNU General Public License v3 (GPLv3)
Classifier: Programming Language :: Python
Classifier: Programming Language :: Python :: 3
Classifier: Programming Language :: Python :: 3.6
Classifier: Programming Language :: Python :: Implementation :: CPython
Classifier: Programming Language :: Python :: Implementation :: PyPy
Requires-Python: >=3.6.0
Requires-Dist: requests
